hyperspace/__init__.py
hyperspace/api_client.py
hyperspace/configuration.py
hyperspace/hyperspace_client.py
hyperspace/rest.py
hyperspace/api/__init__.py
hyperspace/api/hyperspace_api.py
hyperspace/models/__init__.py
hyperspace/models/any_of_update_by_query_query.py
hyperspace/models/auth_dto.py
hyperspace/models/collection_collection_name_body.py
hyperspace/models/collection_name_dsl_search_body.py
hyperspace/models/collection_name_msearch_body.py
hyperspace/models/delete_by_query_request.py
hyperspace/models/delete_by_query_response.py
hyperspace/models/document.py
hyperspace/models/login_dto.py
hyperspace/models/script.py
hyperspace/models/status_dto.py
hyperspace/models/update_by_query.py
test/__init__.py
test/test_any_of_update_by_query_query.py
test/test_auth_dto.py
test/test_collection_collection_name_body.py
test/test_collection_name_dsl_search_body.py
test/test_collection_name_msearch_body.py
test/test_delete_by_query_request.py
test/test_delete_by_query_response.py
test/test_document.py
test/test_hyperspace_api.py
test/test_login_dto.py
test/test_script.py
test/test_status_dto.py
test/test_update_by_query.py
hyperspace_py-2.0.319.dist-info/METADATA
hyperspace_py-2.0.319.dist-info/WHEEL
hyperspace_py-2.0.319.dist-info/top_level.txt
hyperspace_py-2.0.319.dist-info/RECORD
