Metadata-Version: 2.4
Name: hyperspace-py
Version: 2.0.319
Summary: Vector Similarity Demo
Home-page: 
Author-email: support@hyper-space.io
Keywords: Swagger,Vector Similarity Demo
Requires-Dist: certifi>=14.05.14
Requires-Dist: six>=1.10
Requires-Dist: python_dateutil>=2.5.3
Requires-Dist: setuptools>=21.0.0
Requires-Dist: urllib3>=1.15.1
Requires-Dist: msgpack
Dynamic: author-email
Dynamic: description
Dynamic: keywords
Dynamic: requires-dist
Dynamic: summary
